LICENSE
README.md
setup.py
ststools/__init__.py
ststools/base.py
ststools/nanonis_load.py
ststools/nanosurf_load.py
ststools/omicron_load.py
ststools/open_nid.py
ststools.egg-info/PKG-INFO
ststools.egg-info/SOURCES.txt
ststools.egg-info/dependency_links.txt
ststools.egg-info/requires.txt
ststools.egg-info/top_level.txt