Metadata-Version: 2.1
Name: ststools
Version: 6.3.6
Summary: Visualizacao de sts nanosurf, omicron e nanonis
Author: Rafael Reis Barreto
Author-email: rafinhareis17@gmail.com
License: MIT License
Keywords: nanosurf,omicron,sts
License-File: LICENSE
Requires-Dist: pandas
Requires-Dist: numpy
Requires-Dist: scipy
Requires-Dist: matplotlib
Requires-Dist: ipywidgets
Requires-Dist: Pillow
Requires-Dist: scikit-learn
Requires-Dist: igor
Requires-Dist: h5py
Requires-Dist: NSFopen
